runinside/__init__.py
runinside/cli.py
runinside/runinside.py
runinside/tarprep.py
runinside-0.1.0.dist-info/AUTHORS.rst
runinside-0.1.0.dist-info/LICENSE
runinside-0.1.0.dist-info/METADATA
runinside-0.1.0.dist-info/WHEEL
runinside-0.1.0.dist-info/entry_points.txt
runinside-0.1.0.dist-info/top_level.txt
runinside-0.1.0.dist-info/RECORD
